aiobsonrpc/__init__.py
aiobsonrpc/definitions.py
aiobsonrpc/exceptions.py
aiobsonrpc/framing.py
aiobsonrpc/interfaces.py
aiobsonrpc/log.py
aiobsonrpc/misc.py
aiobsonrpc/options.py
aiobsonrpc/rpc.py
aiobsonrpc/socket_queue.py
aiobsonrpc/util.py
aiobsonrpc-0.0.4.dist-info/LICENSE
aiobsonrpc-0.0.4.dist-info/METADATA
aiobsonrpc-0.0.4.dist-info/WHEEL
aiobsonrpc-0.0.4.dist-info/top_level.txt
aiobsonrpc-0.0.4.dist-info/RECORD
