Metadata-Version: 2.1
Name: aiobsonrpc
Version: 0.0.4
Summary: A Python library for JSON-RPC 2.0
Home-page: https://github.com/HarryHEi/aiobsonrpc
Author: DarHarry
Author-email: harryx520@qq.com
License: UNKNOWN
Platform: UNKNOWN
Classifier: Programming Language :: Python :: 3.6
Classifier: License :: OSI Approved :: MIT License
Classifier: Operating System :: OS Independent
